live_serial-0.1.7.data/scripts/livemon.py
live_serial-0.1.7.dist-info/DESCRIPTION.rst
live_serial-0.1.7.dist-info/METADATA
live_serial-0.1.7.dist-info/RECORD
live_serial-0.1.7.dist-info/WHEEL
live_serial-0.1.7.dist-info/metadata.json
live_serial-0.1.7.dist-info/top_level.txt
liveserial/__init__.py
liveserial/base.py
liveserial/config.py
liveserial/livemon.py
liveserial/log.py
liveserial/logging.py
liveserial/monitor.py
liveserial/msg.py
liveserial/plotting.py
liveserial/simport.py
liveserial/simulator.py
