Metadata-Version: 2.0
Name: live-serial
Version: 0.1.7
Summary: Real-time serial port plotter/logger.
Home-page: https://github.com/rosenbrockc/live-serial
Author: Conrad W Rosenbrock
Author-email: rosenbrockc@gmail.com
License: MIT
Platform: UNKNOWN
Classifier: Development Status :: 2 - Pre-Alpha
Classifier: Intended Audience :: Science/Research
Classifier: Natural Language :: English
Classifier: Operating System :: MacOS
Classifier: Operating System :: Microsoft :: Windows
Classifier: Programming Language :: Python
Classifier: Programming Language :: Python :: 2
Classifier: Programming Language :: Python :: 2.7
Classifier: Programming Language :: Python :: 3
Classifier: Programming Language :: Python :: 3.5
Requires-Dist: argparse
Requires-Dist: matplotlib
Requires-Dist: numpy
Requires-Dist: pyserial
Requires-Dist: termcolor
